LICENSE
README.md
setup.py
setuptools_dummy-0.1.0.4-py2.7.egg
disqus_sync/__init__.py
disqus_sync/conf.py
disqus_sync/loader.py
disqus_sync/models.py
disqus_sync/tasks.py
disqus_sync/management/__init__.py
disqus_sync/management/commands/__init__.py
disqus_sync/management/commands/disqus_sync.py
disqus_sync/templates/disqus_sync/comment.html
disqus_sync/templates/disqus_sync/comments.html
disqus_sync/templatetags/__init__.py
disqus_sync/templatetags/disqus_sync.py
django_disqus_sync.egg-info/PKG-INFO
django_disqus_sync.egg-info/SOURCES.txt
django_disqus_sync.egg-info/dependency_links.txt
django_disqus_sync.egg-info/requires.txt
django_disqus_sync.egg-info/top_level.txt