Metadata-Version: 1.1
Name: django-disqus-sync
Version: 1.0.3
Summary: Sync Disqus comments to your database and render them as HTML for better SEO
Home-page: UNKNOWN
Author: Filip Varecha
Author-email: xaralis@centrum.cz
License: GPLv2
Platform: UNKNOWN
Classifier: Development Status :: 4 - Beta
Classifier: Intended Audience :: Developers
Classifier: License :: OSI Approved :: BSD License
Classifier: Operating System :: OS Independent
Classifier: Framework :: Django
Classifier: Programming Language :: Python :: 2.7
Classifier: Operating System :: OS Independent
Classifier: Topic :: Internet :: WWW/HTTP :: Dynamic Content
Classifier: Topic :: Software Development :: Libraries :: Python Modules
